dashboard_compiler/__init__.py
dashboard_compiler/cli.py
dashboard_compiler/cli_context.py
dashboard_compiler/cli_local.py
dashboard_compiler/cli_options.py
dashboard_compiler/cli_output.py
dashboard_compiler/cli_remote.py
dashboard_compiler/controls/__init__.py
dashboard_compiler/controls/compile.py
dashboard_compiler/controls/config.py
dashboard_compiler/controls/types.py
dashboard_compiler/controls/view.py
dashboard_compiler/dashboard/__init__.py
dashboard_compiler/dashboard/compile.py
dashboard_compiler/dashboard/config.py
dashboard_compiler/dashboard/view.py
dashboard_compiler/dashboard_compiler.py
dashboard_compiler/filters/__init__.py
dashboard_compiler/filters/compile.py
dashboard_compiler/filters/config.py
dashboard_compiler/filters/view.py
dashboard_compiler/kibana_client.py
dashboard_compiler/loader.py
dashboard_compiler/lsp/__init__.py
dashboard_compiler/lsp/grid_extractor.py
dashboard_compiler/lsp/grid_updater.py
dashboard_compiler/lsp/server.py
dashboard_compiler/lsp/utils.py
dashboard_compiler/panels/__init__.py
dashboard_compiler/panels/auto_layout.py
dashboard_compiler/panels/base.py
dashboard_compiler/panels/charts/__init__.py
dashboard_compiler/panels/charts/base/__init__.py
dashboard_compiler/panels/charts/base/compile.py
dashboard_compiler/panels/charts/base/config.py
dashboard_compiler/panels/charts/base/view.py
dashboard_compiler/panels/charts/compile.py
dashboard_compiler/panels/charts/config.py
dashboard_compiler/panels/charts/datatable/__init__.py
dashboard_compiler/panels/charts/datatable/compile.py
dashboard_compiler/panels/charts/datatable/config.py
dashboard_compiler/panels/charts/datatable/view.py
dashboard_compiler/panels/charts/esql/columns/__init__.py
dashboard_compiler/panels/charts/esql/columns/compile.py
dashboard_compiler/panels/charts/esql/columns/config.py
dashboard_compiler/panels/charts/esql/columns/view.py
dashboard_compiler/panels/charts/gauge/__init__.py
dashboard_compiler/panels/charts/gauge/compile.py
kb_dashboard_compiler-0.1.10.dist-info/WHEEL
kb_dashboard_compiler-0.1.10.dist-info/entry_points.txt
kb_dashboard_compiler-0.1.10.dist-info/METADATA
kb_dashboard_compiler-0.1.10.dist-info/RECORD
