Metadata-Version: 2.3
Name: kb-dashboard-compiler
Version: 0.1.10
Summary: Compiles dashboard definitions from YAML to Kibana format
License: MIT
Classifier: Development Status :: 3 - Alpha
Classifier: Intended Audience :: Developers
Classifier: License :: OSI Approved :: MIT License
Classifier: Programming Language :: Python :: 3
Classifier: Programming Language :: Python :: 3.12
Classifier: Topic :: Software Development :: Code Generators
Requires-Dist: pyyaml>=6.0.3
Requires-Dist: pydantic>=2.12
Requires-Dist: beartype>=0.22
Requires-Dist: humanize>=4.15
Requires-Dist: click>=8.3
Requires-Dist: rich-click>=1.9.0
Requires-Dist: aiohttp>=3.13
Requires-Dist: prison>=0.2.1
Requires-Dist: elasticsearch>=8.16.2
Requires-Dist: pygls>=2.0.0
Requires-Dist: lsprotocol>=2024.0.0
Requires-Dist: tatsu>=5.15
Requires-Python: >=3.12
